ctrlplane/__init__.py
ctrlplane/client.py
ctrlplane/errors.py
ctrlplane/py.typed
ctrlplane/types.py
ctrlplane/api/__init__.py
ctrlplane/api/default/__init__.py
ctrlplane/api/default/acknowledge_agent_job.py
ctrlplane/api/default/acknowledge_job.py
ctrlplane/api/default/create_environment.py
ctrlplane/api/default/create_release.py
ctrlplane/api/default/create_release_channel.py
ctrlplane/api/default/delete_target.py
ctrlplane/api/default/delete_target_by_identifier.py
ctrlplane/api/default/get_agent_running_job.py
ctrlplane/api/default/get_job.py
ctrlplane/api/default/get_next_jobs.py
ctrlplane/api/default/get_target.py
ctrlplane/api/default/get_target_by_identifier.py
ctrlplane/api/default/set_target_providers_targets.py
ctrlplane/api/default/update_job.py
ctrlplane/api/default/update_job_agent.py
ctrlplane/api/default/update_target.py
ctrlplane/api/default/upsert_target_provider.py
ctrlplane/api/default/upsert_targets.py
ctrlplane/models/__init__.py
ctrlplane/models/acknowledge_agent_job_response_200.py
ctrlplane/models/acknowledge_agent_job_response_200_job.py
ctrlplane/models/acknowledge_agent_job_response_401.py
ctrlplane/models/acknowledge_agent_job_response_404.py
ctrlplane/models/acknowledge_job_response_200.py
ctrlplane/models/acknowledge_job_response_401.py
ctrlplane/models/create_environment_body.py
ctrlplane/models/create_environment_body_release_channels_item.py
ctrlplane/models/create_environment_body_target_filter.py
ctrlplane/models/create_environment_response_200.py
ctrlplane/models/create_environment_response_200_environment.py
ctrlplane/models/create_environment_response_200_environment_target_filter.py
ctrlplane/models/create_environment_response_409.py
ctrlplane/models/create_environment_response_500.py
ctrlplane/models/create_release_body.py
ctrlplane/models/create_release_body_metadata.py
ctrlplane/models/create_release_channel_body.py
ctrlplane/models/create_release_channel_body_release_filter.py
ctrlplane-0.1.1.dist-info/METADATA
ctrlplane-0.1.1.dist-info/WHEEL
ctrlplane-0.1.1.dist-info/RECORD
