Metadata-Version: 2.3
Name: ctrlplane
Version: 0.1.1
Summary: A client library for accessing Ctrlplane API
Project-URL: Source, https://github.com/ctrlplanedev/python
Project-URL: Bug Reports, https://github.com/ctrlplanedev/ctrlplane/issues
Project-URL: Documentation, https://docs.ctrlplane.dev/
Author-email: Ctrlplane <support@ctrlplane.dev>
Classifier: Development Status :: 5 - Production/Stable
Classifier: Intended Audience :: Developers
Classifier: Programming Language :: Go
Classifier: Programming Language :: Python :: 3
Classifier: Programming Language :: Python :: 3 :: Only
Classifier: Programming Language :: Python :: 3.12
Classifier: Topic :: Software Development :: Libraries :: Python Modules
Requires-Python: >=3.7
Requires-Dist: attrs>=21.3.0
Requires-Dist: httpx<0.28.0,>=0.20.0
Requires-Dist: python-dateutil>=2.8.0
